hd_data/__init__.py
hd_data/admin.py
hd_data/apps.py
hd_data/djangoldp_urls.py
hd_data/models.py
hd_data/tests.py
hd_data/views.py
hd_data/migrations/0001_initial.py
hd_data/migrations/0002_auto_20190904_1622.py
hd_data/migrations/0003_auto_20191018_1614.py
hd_data/migrations/__init__.py
hd_data/templates/client_email.txt
hd_data/templates/contact_email.txt
hd_data-0.1.22.dist-info/METADATA
hd_data-0.1.22.dist-info/WHEEL
hd_data-0.1.22.dist-info/top_level.txt
hd_data-0.1.22.dist-info/RECORD
