Metadata-Version: 2.1
Name: hd-data
Version: 0.1.22
Summary: Happy Dev website data
Home-page: UNKNOWN
Author: UNKNOWN
Author-email: UNKNOWN
License: MIT
Platform: UNKNOWN
Classifier: Programming Language :: Python :: 3
Requires-Dist: Pillow (==5.0.0)
